price_process/__init__.py
price_process/helpers.py
price_process/ising.py
price_process/process.py
price_process-1.1.3.dist-info/LICENSE
price_process-1.1.3.dist-info/METADATA
price_process-1.1.3.dist-info/WHEEL
price_process-1.1.3.dist-info/top_level.txt
price_process-1.1.3.dist-info/RECORD
