Metadata-Version: 2.1
Name: price-process
Version: 1.1.3
Summary: Library for generating various stochastic price sequences 
Home-page: https://github.com/borab96/price_process
Author: Bora Basa
Author-email: borabasa@gmail.com
License: MIT
Keywords: finance,stochastic process,mathematical finance,SDE,investing,trading
Platform: UNKNOWN
Requires: numpy
Requires: scipy
Requires: matplotlib
Requires: tqdm
Requires-Python: >=3
License-File: LICENSE
Requires-Dist: numpy
Requires-Dist: scipy
Requires-Dist: matplotlib
Requires-Dist: tqdm
